LICENSE.md
MANIFEST.in
README.md
requirements.txt
setup.py
docs/dmap_intro.ipynb
mapalign/__init__.py
mapalign/align.py
mapalign/dist.py
mapalign/embed.py
mapalign.egg-info/PKG-INFO
mapalign.egg-info/SOURCES.txt
mapalign.egg-info/dependency_links.txt
mapalign.egg-info/requires.txt
mapalign.egg-info/top_level.txt
mapalign/tests/__init__.py
mapalign/tests/test_embed.py