Metadata-Version: 1.2
Name: mapalign
Version: 0.3.0
Summary: Mapalign
Home-page: https://github.com/satra/mapalign
Author: satra
License: Apache License, 2.0
Platform: UNKNOWN
Provides: mapalign
Requires-Python: >=3.6
